next_gen_ui_mcp/__init__.py
next_gen_ui_mcp/__main__.py
next_gen_ui_mcp/agent.py
next_gen_ui_mcp/spec_schema.py
next_gen_ui_mcp/types.py
next_gen_ui_mcp-0.3.0.dist-info/METADATA
next_gen_ui_mcp-0.3.0.dist-info/WHEEL
next_gen_ui_mcp-0.3.0.dist-info/namespace_packages.txt
next_gen_ui_mcp-0.3.0.dist-info/top_level.txt
next_gen_ui_mcp-0.3.0.dist-info/RECORD
